manasafiles/__init__.py
manasafiles/decorators.py
manasafiles/functions.py
manasafiles-154.dist-info/LICENSE
manasafiles-154.dist-info/METADATA
manasafiles-154.dist-info/WHEEL
manasafiles-154.dist-info/top_level.txt
manasafiles-154.dist-info/RECORD
