Metadata-Version: 2.1
Name: manasafiles
Version: 154
Summary: Testing installation of Package
Home-page: https://github.com/manasabalagoni/python-second
Author: manasa
Author-email: manasabalagoni1@gmail.com
License: MIT
Project-URL: Bug Tracker, https://github.com/manasabalagoni/python-second/issues
License-File: LICENSE
Requires-Dist: requests
